django_mksuperuser/__init__.py
django_mksuperuser/models.py
django_mksuperuser/migrations/0001_createsuperuser.py
django_mksuperuser/migrations/__init__.py
django_mksuperuser/fixtures/initial_data.json
django_mksuperuser-0.1.8.dist-info/top_level.txt
django_mksuperuser-0.1.8.dist-info/METADATA
django_mksuperuser-0.1.8.dist-info/DESCRIPTION.rst
django_mksuperuser-0.1.8.dist-info/metadata.json
django_mksuperuser-0.1.8.dist-info/WHEEL
django_mksuperuser-0.1.8.dist-info/RECORD
