Metadata-Version: 2.0
Name: django-mksuperuser
Version: 0.1.8
Summary: Make super user with fixtures or migrations
Home-page: https://github.com/inirudebwoy/django-mksuperuser
Author: Michal Klich
Author-email: michal@michalklich.com
License: UNKNOWN
Platform: UNKNOWN
Classifier: Development Status :: 4 - Beta
Classifier: Environment :: Web Environment
Classifier: Intended Audience :: Developers
Classifier: Framework :: Django
Classifier: Operating System :: OS Independent
Classifier: Programming Language :: Python
Classifier: Programming Language :: Python :: 2
Classifier: Programming Language :: Python :: 2.7
Classifier: Topic :: Software Development :: Libraries :: Python Modules
